prodconpattern/__init__.py
prodconpattern-0.2.1.dist-info/METADATA
prodconpattern-0.2.1.dist-info/RECORD
prodconpattern-0.2.1.dist-info/WHEEL
prodconpattern-0.2.1.dist-info/top_level.txt
test/__init__.py
test/test_two_instance.py
