Metadata-Version: 2.1
Name: prodconpattern
Version: 0.2.1
Summary: 通过装饰器方式实现生产者消费者模式。可以作用于函数、类的方法上，使其变为异步调用，同时，转变为逐次调用，批量执行。方便将零碎的调用转变为批量形势进行统一执行。
Home-page: https://github.com/mmmaaaggg/ProducerConsumerPattern
Author: MG
Author-email: mmmaaaggg@163.com
License: UNKNOWN
Platform: UNKNOWN
Classifier: Programming Language :: Python :: 3 :: Only
Classifier: Programming Language :: Python :: 3.4
Classifier: Programming Language :: Python :: 3.5
Classifier: Programming Language :: Python :: 3.6
Classifier: Programming Language :: Python :: 3.7
Classifier: License :: OSI Approved :: MIT License
Classifier: Development Status :: 5 - Production/Stable
Classifier: Environment :: No Input/Output (Daemon)
Classifier: Intended Audience :: Developers
Classifier: Natural Language :: Chinese (Simplified)
Classifier: Topic :: Software Development
Requires-Python: >=3.4
